{
  "ENVIRONMENT_NAME": "QA",
  //BE CAREFUL NAMING VARIBLES. E.G. USERNAME is a variable set to your computer username, confirm this by running `echo %USERNAME%` on the command prompt
  "BROWSER": "Chrome",

  "HOST": "https://biberk-apollo-qa.azurewebsites.net",
  "SERVER_HOST": "https://bibaoqa-fd.azurefd.net/api",

  "APP_KEYVAULT_URI": "https://xbibaoazckv-qa.vault.azure.net/",
  "KEYVAULT_URI": "https://xbibaoazckv-automationqa.vault.azure.net/",

  "AZUREDEVOPS_ORGANIZATION": "biberk",
  "AZUREDEVOPS_PROJECT": "Apollo",
  "AZUREDEVOPS_TESTPLAN_ID": "10364",
  "AZUREDEVOPS_TESTSUITE_ID": "15133",

  "COSMOS_TARGETURL_SECRETNAME": "CosmosDB-EndpointUrl",
  "COSMOS_APIKEY_SECRETNAME": "CosmosDB-AuthorizationKey",

  "SQL_CONNECTIONSTRING_SECRETNAME": "ApolloSQL",

  "CURRENT_SEVERITY_LEVEL": "Debug",

  "HIGHLIGHT_ON": "true",

  "LOADING_SCREEN_XPATH": "//bh-mat-spinner-overlay/*",

  "API_TENANT_ID_SECRETNAME": "force-field-proxy-ida-tenant",
  "API_CLIENT_ID_SECRETNAME": "force-field-proxy-ida-client-id",
  "API_CLIENT_SECRET_SECRETNAME": "force-field-proxy-ida-client-secret",
  "API_USERNAME_SECRETNAME": "ApolloUsername",
  "API_PASSWORD_SECRETNAME": "TestPassword2",
  "CAB_BASEURL_SECRETNAME": "CabApi-BaseUrl",
  "CAB_API_KEY_SECRETNAME": "CabApi-Key"
}
